tintin_lua_py/__init__.py
tintin_lua_py/cli.py
tintin_lua_py/bin/tt++
tintin_lua_py-2.2.51.dist-info/METADATA
tintin_lua_py-2.2.51.dist-info/WHEEL
tintin_lua_py-2.2.51.dist-info/entry_points.txt
tintin_lua_py-2.2.51.dist-info/top_level.txt
tintin_lua_py-2.2.51.dist-info/RECORD
